mxdevtool.libs/libcrypt-830b89a5.so.2
mxdevtool-1.0.32.3.dist-info/METADATA
mxdevtool-1.0.32.3.dist-info/WHEEL
mxdevtool-1.0.32.3.dist-info/top_level.txt
mxdevtool-1.0.32.3.dist-info/RECORD
mxdevtool-1.0.32.3.data/data/share/doc/quantlib/LICENSE.TXT
mxdevtool/utils.py
mxdevtool/mxdevtool.py
mxdevtool/config.py
mxdevtool/package_info.ini
mxdevtool/__init__.py
mxdevtool/_mxdevtool.cpython-310-x86_64-linux-gnu.so
mxdevtool/data/__init__.py
mxdevtool/data/providers/bloomberg.py
mxdevtool/data/providers/sample.py
mxdevtool/data/providers/__init__.py
mxdevtool/data/repositories/repo.py
mxdevtool/data/repositories/settings.py
mxdevtool/data/repositories/__init__.py
mxdevtool/quotes/__init__.py
mxdevtool/xenarix/calibration.py
mxdevtool/xenarix/core.py
mxdevtool/xenarix/pathcalc.py
mxdevtool/xenarix/sample.py
mxdevtool/xenarix/__init__.py
mxdevtool/shock/traits.py
mxdevtool/shock/__init__.py
mxdevtool/marketconvension/core.py
mxdevtool/marketconvension/__init__.py
mxdevtool/termstructures/yieldcurve.py
mxdevtool/termstructures/volts.py
mxdevtool/termstructures/__init__.py
mxdevtool/instruments/pricing.py
mxdevtool/instruments/outputs.py
mxdevtool/instruments/options.py
mxdevtool/instruments/structured.py
mxdevtool/instruments/swap.py
mxdevtool/instruments/__init__.py
mxdevtool/convension/__init__.py
mxdevtool/view/reports.py
mxdevtool/view/charts.py
mxdevtool/view/__init__.py
