Metadata-Version: 2.1
Name: mxdevtool
Version: 1.0.32.3
Summary: Python bindings for the MxDevTool library
Home-page: https://www.montrix.co.kr
Maintainer: Montrix Developers
Maintainer-email: master@montrix.co.kr
License: Montrix Non-Commercial License
Platform: Windows
Platform: Linux
Platform: MacOS
Classifier: Development Status :: 4 - Beta
Classifier: Environment :: Console
Classifier: Intended Audience :: Developers
Classifier: Intended Audience :: Science/Research
Classifier: Intended Audience :: End Users/Desktop
Classifier: Natural Language :: English
Classifier: Programming Language :: C++
Classifier: Programming Language :: Python
Classifier: Topic :: Scientific/Engineering
Classifier: Operating System :: Microsoft :: Windows
Classifier: Operating System :: POSIX :: Linux
Classifier: Operating System :: MacOS
